wciwt/__init__.py
wciwt-0.2.dist-info/DESCRIPTION.rst
wciwt-0.2.dist-info/METADATA
wciwt-0.2.dist-info/RECORD
wciwt-0.2.dist-info/WHEEL
wciwt-0.2.dist-info/entry_points.txt
wciwt-0.2.dist-info/metadata.json
wciwt-0.2.dist-info/top_level.txt
