Metadata-Version: 2.0
Name: wciwt
Version: 0.2
Summary: wciwt is a command line tool which makes it easier to find your favorite TV shows and movies in India. It currently supports Netflix, Prime Video and Hotstar.
Home-page: UNKNOWN
Author: Ajay
Author-email: ajaymkatte95@gmail.com
License: UNKNOWN
Download-URL: https://github.com/howdyauthors/wciwt
Platform: UNKNOWN
Requires-Dist: requests
